Am_serializer/Ser.py
Am_serializer/__init__.py
Am_serializer/constants.py
Am_serializer/json_utils.py
Am_serializer/pack_utils.py
Am_serializer/serializer.py
Am_serializer/unpack_utils.py
Am_serializer/xml_utils.py
ArteomSer-0.9.0.dist-info/METADATA
ArteomSer-0.9.0.dist-info/WHEEL
ArteomSer-0.9.0.dist-info/entry_points.txt
ArteomSer-0.9.0.dist-info/top_level.txt
ArteomSer-0.9.0.dist-info/RECORD
