Metadata-Version: 2.1
Name: ArteomSer
Version: 0.9.0
Summary: JSON and XLM serializer
Home-page: UNKNOWN
Author: Arteom Maksimchikau
Author-email: maksimchikov03@mail.ru
License: UNKNOWN
Platform: UNKNOWN
